vibeshub/__init__.py
vibeshub/list_utils.py
vibeshub_core-0.2.0.dist-info/LICENSE
vibeshub_core-0.2.0.dist-info/METADATA
vibeshub_core-0.2.0.dist-info/WHEEL
vibeshub_core-0.2.0.dist-info/top_level.txt
vibeshub_core-0.2.0.dist-info/RECORD
