Metadata-Version: 2.1
Name: vibeshub-core
Version: 0.2.0
Summary: Core utility functions for the VibesHub ecosystem.
Home-page: https://github.com/vibeshub-org/vibeshub-core
Author: Iliyan Slavchov
Author-email: yani.slavchov@gmail.com
Classifier: Programming Language :: Python :: 3
Classifier: License :: OSI Approved :: MIT License
Classifier: Operating System :: OS Independent
Requires-Python: >=3.7
License-File: LICENSE
